pandoc_codeblock_include/__init__.py
pandoc_codeblock_include/_main.py
pandoc_codeblock_include-1.1.0.0.dist-info/METADATA
pandoc_codeblock_include-1.1.0.0.dist-info/WHEEL
pandoc_codeblock_include-1.1.0.0.dist-info/entry_points.txt
pandoc_codeblock_include-1.1.0.0.dist-info/licenses/LICENSE
pandoc_codeblock_include-1.1.0.0.dist-info/RECORD
