Metadata-Version: 2.4
Name: pandoc-codeblock-include
Version: 1.1.0.0
Summary: A pandoc filter for including file in block code
Project-URL: Homepage, https://github.com/chdemko/pandoc-codeblock-include
Project-URL: Documentation, https://pandoc-codeblock-include.readthedocs.io/
Project-URL: Repository, https://github.com/chdemko/pandoc-codeblock-include
Project-URL: Issues, https://github.com/chdemko/pandoc-codeblock-include/issues
Author-email: Christophe Demko <chdemko@gmail.com>
Maintainer-email: Christophe Demko <chdemko@gmail.com>
License: BSD-3-Clause
License-File: LICENSE
Keywords: codeblock,filters,include,pandoc
Classifier: Development Status :: 5 - Production/Stable
Classifier: Environment :: Console
Classifier: Intended Audience :: Developers
Classifier: Intended Audience :: End Users/Desktop
Classifier: Natural Language :: English
Classifier: Operating System :: OS Independent
Classifier: Programming Language :: Python :: 3.10
Classifier: Programming Language :: Python :: 3.11
Classifier: Programming Language :: Python :: 3.12
Classifier: Programming Language :: Python :: 3.13
Classifier: Topic :: Software Development :: Build Tools
Classifier: Topic :: Software Development :: Documentation
Classifier: Topic :: Text Processing :: Filters
Requires-Python: <3.14,>=3.10
Requires-Dist: panflute~=2.3
